{
  "meta": {
    "title": "Reset Password"
  },
  "queryParams": [
    {
      "name": "token",
      "value": ""
    }
  ],
  "layout": "store",
  "content": {
    "type": "Box",
    "props": {
      "className": "flex flex-1 w-full items-center justify-center px-[16px] flex-col"
    },
    "children": [
      {
        "type": "Box",
        "props": {
          "className": "w-full max-w-[448px] min-w-0 space-y-[24px] flex flex-col"
        },
        "children": [
          {
            "type": "Box",
            "props": {
              "className": "space-y-[8px] text-center flex-col"
            },
            "children": [
              {
                "type": "Text",
                "props": {
                  "className": "text-[30px] font-bold text-center flex-col"
                },
                "text": "Set New Password"
              },
              {
                "type": "Text",
                "props": {
                  "className": "text-[var(--theme-muted-foreground)] text-center flex-col"
                },
                "text": "Choose a strong new password for your account."
              }
            ]
          },
          {
            "type": "Box",
            "props": {
              "className": "w-full rounded-[12px] border-[1px] border-[var(--theme-border)] bg-[var(--theme-card)] py-[24px] shadow-sm flex-col"
            },
            "children": [
              {
                "type": "Box",
                "props": {
                  "className": "px-[24px] space-y-[16px] flex-col"
                },
                "children": [
                  {
                    "type": "Box",
                    "props": {
                      "className": "space-y-[8px] flex-col"
                    },
                    "children": [
                      {
                        "type": "Text",
                        "props": {
                          "className": "text-[14px] font-medium leading-none flex-col"
                        },
                        "text": "New Password"
                      },
                      {
                        "type": "Input",
                        "id": "3290cf68-5a8f-43bd-846f-1409a9e166b5",
                        "props": {
                          "variant": "outline",
                          "size": "sm",
                          "className": "!text-[var(--theme-foreground)] flex-col",
                          "placeholder": "••••••••",
                          "placeholderTextColor": "#9ca3af",
                          "name": "password",
                          "secureTextEntry": true
                        },
                        "children": []
                      }
                    ]
                  },
                  {
                    "type": "Box",
                    "props": {
                      "className": "space-y-[8px] flex-col"
                    },
                    "children": [
                      {
                        "type": "Text",
                        "props": {
                          "className": "text-[14px] font-medium leading-none flex-col"
                        },
                        "text": "Confirm Password"
                      },
                      {
                        "type": "Input",
                        "id": "c9456c08-4445-435c-a38d-f658c48a4e9f",
                        "props": {
                          "variant": "outline",
                          "size": "sm",
                          "className": "!text-[var(--theme-foreground)] flex-col",
                          "placeholder": "••••••••",
                          "placeholderTextColor": "#9ca3af",
                          "name": "confirmPassword",
                          "secureTextEntry": true
                        },
                        "children": []
                      }
                    ]
                  },
                  {
                    "type": "Box",
                    "props": {
                      "className": "text-[14px] text-red-500 flex-col"
                    },
                    "condition": "_workflow?.lastError",
                    "children": [
                      {
                        "type": "Text",
                        "text": "{{_workflow.lastError}}"
                      }
                    ]
                  },
                  {
                    "type": "Box",
                    "props": {
                      "className": "w-full !bg-[var(--theme-primary)] hover:!bg-[var(--theme-primary)] !text-white flex flex-row items-center justify-center py-[12px] rounded-[6px]"
                    },
                    "children": [
                      {
                        "type": "Text",
                        "props": {
                          "className": "text-white flex-col"
                        },
                        "text": "Reset Password"
                      }
                    ],
                    "actions": [
                      {
                        "trigger": "click",
                        "workflowId": "a0b1c2d3-e4f5-6789-abcd-012345678901"
                      }
                    ]
                  }
                ]
              }
            ]
          }
        ]
      }
    ]
  }
}
